scrapper_boilerplate/__init__.py
scrapper_boilerplate/account/__init__.py
scrapper_boilerplate/build/__init__.py
scrapper_boilerplate/cookies/__init__.py
scrapper_boilerplate/file_handler/__init__.py
scrapper_boilerplate/output/__init__.py
scrapper_boilerplate/parser_handler/__init__.py
scrapper_boilerplate/proxy/__init__.py
scrapper_boilerplate/setup/__init__.py
scrapper_boilerplate/telegram/__init__.py
scrapper_boilerplate/timer/__init__.py
scrapper_boilerplate/warnings/__init__.py
scrapper_boilerplate/webdriver_handler/__init__.py
tests/__init__.py
tests/test_chromedriver.py
tests/test_log.py
tests/request/__init__.py
tests/request/test_get_request.py
tests/telegram/__init__.py
tests/telegram/test_message.py
tests/telegram/test_send_file.py
tests/webdriver/__init__.py
tests/webdriver/test_explicitly_wait.py
tests/webdriver/test_load_dynamic_page.py
tests/webdriver/test_scroll.py
tests/webdriver/test_scroll_with.py
scrapper_boilerplate-0.2.13.dist-info/METADATA
scrapper_boilerplate-0.2.13.dist-info/WHEEL
scrapper_boilerplate-0.2.13.dist-info/top_level.txt
scrapper_boilerplate-0.2.13.dist-info/RECORD
