Metadata-Version: 2.1
Name: scrapper-boilerplate
Version: 0.2.13
Summary: Scrapping/Automating tools, userSwitching, anti-bot detection and more...
Home-page: https://github.com/mx-jeff/scrapper-boilerplate
Author: Jeferson/MxJeff
Author-email: mx.jeferson.10@hotmail.com
Classifier: Intended Audience :: Developers
Classifier: License :: OSI Approved :: MIT License
Classifier: Programming Language :: Python :: 3.10
Classifier: Operating System :: OS Independent
Requires-Dist: selenium
Requires-Dist: requests
Requires-Dist: pandas
Requires-Dist: beautifulsoup4
Requires-Dist: python-dotenv
Requires-Dist: python-telegram-bot
Requires-Dist: lxml
Requires-Dist: webdriver-manager
Requires-Dist: openpyxl
Requires-Dist: pytest
